<?xml version="1.0" encoding="UTF-8"?>
<annotation>
	<filename>dataset/annotations/183.xml</filename>
	<objects>45</objects>
	<object>
		<name>BLACKBIRD</name>
		<box>
			<xmin>183</xmin>
			<ymin>332</ymin>
			<xmax>201</xmax>
			<ymax>356</ymax>
		</box>
	</object>
	<object>
		<name>REDBIRD</name>
		<box>
			<xmin>166</xmin>
			<ymin>382</ymin>
			<xmax>178</xmax>
			<ymax>393</ymax>
		</box>
	</object>
	<object>
		<name>WHITEBIRD</name>
		<box>
			<xmin>108</xmin>
			<ymin>367</ymin>
			<xmax>131</xmax>
			<ymax>394</ymax>
		</box>
	</object>
	<object>
		<name>SLING</name>
		<box>
			<xmin>182</xmin>
			<ymin>337</ymin>
			<xmax>202</xmax>
			<ymax>394</ymax>
		</box>
	</object>
	<object>
		<name>UNKNOWN</name>
		<box>
			<xmin>495</xmin>
			<ymin>394</ymin>
			<xmax>512</xmax>
			<ymax>395</ymax>
		</box>
	</object>
	<object>
		<name>UNKNOWN</name>
		<box>
			<xmin>512</xmin>
			<ymin>394</ymin>
			<xmax>530</xmax>
			<ymax>395</ymax>
		</box>
	</object>
	<object>
		<name>UNKNOWN</name>
		<box>
			<xmin>477</xmin>
			<ymin>394</ymin>
			<xmax>495</xmax>
			<ymax>395</ymax>
		</box>
	</object>
	<object>
		<name>UNKNOWN</name>
		<box>
			<xmin>529</xmin>
			<ymin>394</ymin>
			<xmax>547</xmax>
			<ymax>395</ymax>
		</box>
	</object>
	<object>
		<name>UNKNOWN</name>
		<box>
			<xmin>460</xmin>
			<ymin>394</ymin>
			<xmax>478</xmax>
			<ymax>395</ymax>
		</box>
	</object>
	<object>
		<name>UNKNOWN</name>
		<box>
			<xmin>547</xmin>
			<ymin>394</ymin>
			<xmax>565</xmax>
			<ymax>395</ymax>
		</box>
	</object>
	<object>
		<name>UNKNOWN</name>
		<box>
			<xmin>442</xmin>
			<ymin>394</ymin>
			<xmax>460</xmax>
			<ymax>395</ymax>
		</box>
	</object>
	<object>
		<name>UNKNOWN</name>
		<box>
			<xmin>547</xmin>
			<ymin>394</ymin>
			<xmax>565</xmax>
			<ymax>395</ymax>
		</box>
	</object>
	<object>
		<name>UNKNOWN</name>
		<box>
			<xmin>442</xmin>
			<ymin>394</ymin>
			<xmax>460</xmax>
			<ymax>395</ymax>
		</box>
	</object>
	<object>
		<name>ICE</name>
		<box>
			<xmin>513</xmin>
			<ymin>318</ymin>
			<xmax>525</xmax>
			<ymax>329</ymax>
		</box>
	</object>
	<object>
		<name>STONE</name>
		<box>
			<xmin>482</xmin>
			<ymin>318</ymin>
			<xmax>494</xmax>
			<ymax>329</ymax>
		</box>
	</object>
	<object>
		<name>STONE</name>
		<box>
			<xmin>442</xmin>
			<ymin>387</ymin>
			<xmax>449</xmax>
			<ymax>393</ymax>
		</box>
	</object>
	<object>
		<name>STONE</name>
		<box>
			<xmin>454</xmin>
			<ymin>387</ymin>
			<xmax>460</xmax>
			<ymax>393</ymax>
		</box>
	</object>
	<object>
		<name>STONE</name>
		<box>
			<xmin>468</xmin>
			<ymin>387</ymin>
			<xmax>474</xmax>
			<ymax>393</ymax>
		</box>
	</object>
	<object>
		<name>STONE</name>
		<box>
			<xmin>483</xmin>
			<ymin>387</ymin>
			<xmax>489</xmax>
			<ymax>393</ymax>
		</box>
	</object>
	<object>
		<name>STONE</name>
		<box>
			<xmin>494</xmin>
			<ymin>387</ymin>
			<xmax>500</xmax>
			<ymax>393</ymax>
		</box>
	</object>
	<object>
		<name>STONE</name>
		<box>
			<xmin>507</xmin>
			<ymin>387</ymin>
			<xmax>513</xmax>
			<ymax>393</ymax>
		</box>
	</object>
	<object>
		<name>STONE</name>
		<box>
			<xmin>518</xmin>
			<ymin>387</ymin>
			<xmax>524</xmax>
			<ymax>393</ymax>
		</box>
	</object>
	<object>
		<name>STONE</name>
		<box>
			<xmin>533</xmin>
			<ymin>387</ymin>
			<xmax>539</xmax>
			<ymax>393</ymax>
		</box>
	</object>
	<object>
		<name>STONE</name>
		<box>
			<xmin>548</xmin>
			<ymin>387</ymin>
			<xmax>554</xmax>
			<ymax>393</ymax>
		</box>
	</object>
	<object>
		<name>STONE</name>
		<box>
			<xmin>558</xmin>
			<ymin>387</ymin>
			<xmax>565</xmax>
			<ymax>393</ymax>
		</box>
	</object>
	<object>
		<name>STONE</name>
		<box>
			<xmin>442</xmin>
			<ymin>381</ymin>
			<xmax>500</xmax>
			<ymax>387</ymax>
		</box>
	</object>
	<object>
		<name>STONE</name>
		<box>
			<xmin>507</xmin>
			<ymin>381</ymin>
			<xmax>565</xmax>
			<ymax>387</ymax>
		</box>
	</object>
	<object>
		<name>STONE</name>
		<box>
			<xmin>442</xmin>
			<ymin>374</ymin>
			<xmax>500</xmax>
			<ymax>380</ymax>
		</box>
	</object>
	<object>
		<name>WOOD</name>
		<box>
			<xmin>507</xmin>
			<ymin>374</ymin>
			<xmax>565</xmax>
			<ymax>380</ymax>
		</box>
	</object>
	<object>
		<name>ICE</name>
		<box>
			<xmin>442</xmin>
			<ymin>368</ymin>
			<xmax>500</xmax>
			<ymax>374</ymax>
		</box>
	</object>
	<object>
		<name>ICE</name>
		<box>
			<xmin>507</xmin>
			<ymin>368</ymin>
			<xmax>565</xmax>
			<ymax>374</ymax>
		</box>
	</object>
	<object>
		<name>STONE</name>
		<box>
			<xmin>468</xmin>
			<ymin>355</ymin>
			<xmax>492</xmax>
			<ymax>368</ymax>
		</box>
	</object>
	<object>
		<name>STONE</name>
		<box>
			<xmin>515</xmin>
			<ymin>355</ymin>
			<xmax>539</xmax>
			<ymax>368</ymax>
		</box>
	</object>
	<object>
		<name>STONE</name>
		<box>
			<xmin>468</xmin>
			<ymin>349</ymin>
			<xmax>492</xmax>
			<ymax>355</ymax>
		</box>
	</object>
	<object>
		<name>ICE</name>
		<box>
			<xmin>515</xmin>
			<ymin>349</ymin>
			<xmax>539</xmax>
			<ymax>355</ymax>
		</box>
	</object>
	<object>
		<name>STONE</name>
		<box>
			<xmin>477</xmin>
			<ymin>342</ymin>
			<xmax>489</xmax>
			<ymax>349</ymax>
		</box>
	</object>
	<object>
		<name>ICE</name>
		<box>
			<xmin>518</xmin>
			<ymin>343</ymin>
			<xmax>530</xmax>
			<ymax>349</ymax>
		</box>
	</object>
	<object>
		<name>STONE</name>
		<box>
			<xmin>477</xmin>
			<ymin>336</ymin>
			<xmax>489</xmax>
			<ymax>342</ymax>
		</box>
	</object>
	<object>
		<name>STONE</name>
		<box>
			<xmin>518</xmin>
			<ymin>336</ymin>
			<xmax>530</xmax>
			<ymax>342</ymax>
		</box>
	</object>
	<object>
		<name>ICE</name>
		<box>
			<xmin>480</xmin>
			<ymin>330</ymin>
			<xmax>527</xmax>
			<ymax>336</ymax>
		</box>
	</object>
	<object>
		<name>STONE</name>
		<box>
			<xmin>500</xmin>
			<ymin>305</ymin>
			<xmax>507</xmax>
			<ymax>329</ymax>
		</box>
	</object>
	<object>
		<name>WOOD</name>
		<box>
			<xmin>500</xmin>
			<ymin>281</ymin>
			<xmax>507</xmax>
			<ymax>305</ymax>
		</box>
	</object>
	<object>
		<name>PIG</name>
		<box>
			<xmin>446</xmin>
			<ymin>356</ymin>
			<xmax>459</xmax>
			<ymax>367</ymax>
		</box>
	</object>
	<object>
		<name>PIG</name>
		<box>
			<xmin>549</xmin>
			<ymin>356</ymin>
			<xmax>562</xmax>
			<ymax>367</ymax>
		</box>
	</object>
	<object>
		<name>PIG</name>
		<box>
			<xmin>498</xmin>
			<ymin>270</ymin>
			<xmax>510</xmax>
			<ymax>280</ymax>
		</box>
	</object>
</annotation>
