<?xml version="1.0" encoding="UTF-8"?>
<annotation>
	<filename>dataset/annotations/2522.xml</filename>
	<objects>176</objects>
	<object>
		<name>WHITEBIRD</name>
		<box>
			<xmin>181</xmin>
			<ymin>330</ymin>
			<xmax>203</xmax>
			<ymax>357</ymax>
		</box>
	</object>
	<object>
		<name>REDBIRD</name>
		<box>
			<xmin>166</xmin>
			<ymin>382</ymin>
			<xmax>178</xmax>
			<ymax>393</ymax>
		</box>
	</object>
	<object>
		<name>BLACKBIRD</name>
		<box>
			<xmin>121</xmin>
			<ymin>370</ymin>
			<xmax>139</xmax>
			<ymax>394</ymax>
		</box>
	</object>
	<object>
		<name>YELLOWBIRD</name>
		<box>
			<xmin>103</xmin>
			<ymin>377</ymin>
			<xmax>119</xmax>
			<ymax>392</ymax>
		</box>
	</object>
	<object>
		<name>SLING</name>
		<box>
			<xmin>182</xmin>
			<ymin>337</ymin>
			<xmax>202</xmax>
			<ymax>394</ymax>
		</box>
	</object>
	<object>
		<name>HILL</name>
		<box>
			<xmin>394</xmin>
			<ymin>244</ymin>
			<xmax>412</xmax>
			<ymax>262</ymax>
		</box>
	</object>
	<object>
		<name>HILL</name>
		<box>
			<xmin>411</xmin>
			<ymin>244</ymin>
			<xmax>429</xmax>
			<ymax>262</ymax>
		</box>
	</object>
	<object>
		<name>HILL</name>
		<box>
			<xmin>429</xmin>
			<ymin>244</ymin>
			<xmax>447</xmax>
			<ymax>262</ymax>
		</box>
	</object>
	<object>
		<name>HILL</name>
		<box>
			<xmin>446</xmin>
			<ymin>244</ymin>
			<xmax>464</xmax>
			<ymax>262</ymax>
		</box>
	</object>
	<object>
		<name>HILL</name>
		<box>
			<xmin>464</xmin>
			<ymin>244</ymin>
			<xmax>481</xmax>
			<ymax>262</ymax>
		</box>
	</object>
	<object>
		<name>HILL</name>
		<box>
			<xmin>481</xmin>
			<ymin>244</ymin>
			<xmax>499</xmax>
			<ymax>262</ymax>
		</box>
	</object>
	<object>
		<name>HILL</name>
		<box>
			<xmin>495</xmin>
			<ymin>387</ymin>
			<xmax>512</xmax>
			<ymax>395</ymax>
		</box>
	</object>
	<object>
		<name>HILL</name>
		<box>
			<xmin>512</xmin>
			<ymin>387</ymin>
			<xmax>530</xmax>
			<ymax>395</ymax>
		</box>
	</object>
	<object>
		<name>HILL</name>
		<box>
			<xmin>477</xmin>
			<ymin>387</ymin>
			<xmax>495</xmax>
			<ymax>395</ymax>
		</box>
	</object>
	<object>
		<name>HILL</name>
		<box>
			<xmin>529</xmin>
			<ymin>387</ymin>
			<xmax>547</xmax>
			<ymax>395</ymax>
		</box>
	</object>
	<object>
		<name>HILL</name>
		<box>
			<xmin>460</xmin>
			<ymin>387</ymin>
			<xmax>478</xmax>
			<ymax>395</ymax>
		</box>
	</object>
	<object>
		<name>HILL</name>
		<box>
			<xmin>547</xmin>
			<ymin>387</ymin>
			<xmax>565</xmax>
			<ymax>395</ymax>
		</box>
	</object>
	<object>
		<name>HILL</name>
		<box>
			<xmin>442</xmin>
			<ymin>387</ymin>
			<xmax>460</xmax>
			<ymax>395</ymax>
		</box>
	</object>
	<object>
		<name>HILL</name>
		<box>
			<xmin>564</xmin>
			<ymin>387</ymin>
			<xmax>582</xmax>
			<ymax>395</ymax>
		</box>
	</object>
	<object>
		<name>HILL</name>
		<box>
			<xmin>425</xmin>
			<ymin>387</ymin>
			<xmax>443</xmax>
			<ymax>395</ymax>
		</box>
	</object>
	<object>
		<name>HILL</name>
		<box>
			<xmin>581</xmin>
			<ymin>387</ymin>
			<xmax>599</xmax>
			<ymax>395</ymax>
		</box>
	</object>
	<object>
		<name>HILL</name>
		<box>
			<xmin>408</xmin>
			<ymin>387</ymin>
			<xmax>426</xmax>
			<ymax>395</ymax>
		</box>
	</object>
	<object>
		<name>HILL</name>
		<box>
			<xmin>599</xmin>
			<ymin>387</ymin>
			<xmax>617</xmax>
			<ymax>395</ymax>
		</box>
	</object>
	<object>
		<name>HILL</name>
		<box>
			<xmin>390</xmin>
			<ymin>387</ymin>
			<xmax>408</xmax>
			<ymax>395</ymax>
		</box>
	</object>
	<object>
		<name>HILL</name>
		<box>
			<xmin>616</xmin>
			<ymin>387</ymin>
			<xmax>634</xmax>
			<ymax>395</ymax>
		</box>
	</object>
	<object>
		<name>HILL</name>
		<box>
			<xmin>373</xmin>
			<ymin>387</ymin>
			<xmax>391</xmax>
			<ymax>395</ymax>
		</box>
	</object>
	<object>
		<name>HILL</name>
		<box>
			<xmin>633</xmin>
			<ymin>387</ymin>
			<xmax>651</xmax>
			<ymax>395</ymax>
		</box>
	</object>
	<object>
		<name>HILL</name>
		<box>
			<xmin>356</xmin>
			<ymin>387</ymin>
			<xmax>374</xmax>
			<ymax>395</ymax>
		</box>
	</object>
	<object>
		<name>HILL</name>
		<box>
			<xmin>651</xmin>
			<ymin>387</ymin>
			<xmax>669</xmax>
			<ymax>395</ymax>
		</box>
	</object>
	<object>
		<name>HILL</name>
		<box>
			<xmin>338</xmin>
			<ymin>387</ymin>
			<xmax>356</xmax>
			<ymax>395</ymax>
		</box>
	</object>
	<object>
		<name>HILL</name>
		<box>
			<xmin>651</xmin>
			<ymin>387</ymin>
			<xmax>669</xmax>
			<ymax>395</ymax>
		</box>
	</object>
	<object>
		<name>HILL</name>
		<box>
			<xmin>338</xmin>
			<ymin>387</ymin>
			<xmax>356</xmax>
			<ymax>395</ymax>
		</box>
	</object>
	<object>
		<name>ICE</name>
		<box>
			<xmin>559</xmin>
			<ymin>272</ymin>
			<xmax>581</xmax>
			<ymax>293</ymax>
		</box>
	</object>
	<object>
		<name>ICE</name>
		<box>
			<xmin>364</xmin>
			<ymin>281</ymin>
			<xmax>376</xmax>
			<ymax>293</ymax>
		</box>
	</object>
	<object>
		<name>ICE</name>
		<box>
			<xmin>469</xmin>
			<ymin>164</ymin>
			<xmax>480</xmax>
			<ymax>176</ymax>
		</box>
	</object>
	<object>
		<name>STONE</name>
		<box>
			<xmin>412</xmin>
			<ymin>164</ymin>
			<xmax>424</xmax>
			<ymax>176</ymax>
		</box>
	</object>
	<object>
		<name>STONE</name>
		<box>
			<xmin>545</xmin>
			<ymin>288</ymin>
			<xmax>557</xmax>
			<ymax>300</ymax>
		</box>
	</object>
	<object>
		<name>WOOD</name>
		<box>
			<xmin>431</xmin>
			<ymin>282</ymin>
			<xmax>443</xmax>
			<ymax>293</ymax>
		</box>
	</object>
	<object>
		<name>WOOD</name>
		<box>
			<xmin>517</xmin>
			<ymin>288</ymin>
			<xmax>528</xmax>
			<ymax>299</ymax>
		</box>
	</object>
	<object>
		<name>WOOD</name>
		<box>
			<xmin>583</xmin>
			<ymin>288</ymin>
			<xmax>595</xmax>
			<ymax>300</ymax>
		</box>
	</object>
	<object>
		<name>STONE</name>
		<box>
			<xmin>478</xmin>
			<ymin>288</ymin>
			<xmax>490</xmax>
			<ymax>299</ymax>
		</box>
	</object>
	<object>
		<name>STONE</name>
		<box>
			<xmin>339</xmin>
			<ymin>380</ymin>
			<xmax>351</xmax>
			<ymax>387</ymax>
		</box>
	</object>
	<object>
		<name>STONE</name>
		<box>
			<xmin>364</xmin>
			<ymin>380</ymin>
			<xmax>376</xmax>
			<ymax>387</ymax>
		</box>
	</object>
	<object>
		<name>STONE</name>
		<box>
			<xmin>390</xmin>
			<ymin>380</ymin>
			<xmax>402</xmax>
			<ymax>387</ymax>
		</box>
	</object>
	<object>
		<name>WOOD</name>
		<box>
			<xmin>405</xmin>
			<ymin>380</ymin>
			<xmax>417</xmax>
			<ymax>387</ymax>
		</box>
	</object>
	<object>
		<name>WOOD</name>
		<box>
			<xmin>431</xmin>
			<ymin>380</ymin>
			<xmax>443</xmax>
			<ymax>387</ymax>
		</box>
	</object>
	<object>
		<name>WOOD</name>
		<box>
			<xmin>457</xmin>
			<ymin>380</ymin>
			<xmax>469</xmax>
			<ymax>387</ymax>
		</box>
	</object>
	<object>
		<name>STONE</name>
		<box>
			<xmin>472</xmin>
			<ymin>380</ymin>
			<xmax>484</xmax>
			<ymax>387</ymax>
		</box>
	</object>
	<object>
		<name>STONE</name>
		<box>
			<xmin>498</xmin>
			<ymin>380</ymin>
			<xmax>510</xmax>
			<ymax>387</ymax>
		</box>
	</object>
	<object>
		<name>STONE</name>
		<box>
			<xmin>523</xmin>
			<ymin>380</ymin>
			<xmax>535</xmax>
			<ymax>387</ymax>
		</box>
	</object>
	<object>
		<name>WOOD</name>
		<box>
			<xmin>539</xmin>
			<ymin>380</ymin>
			<xmax>551</xmax>
			<ymax>387</ymax>
		</box>
	</object>
	<object>
		<name>WOOD</name>
		<box>
			<xmin>564</xmin>
			<ymin>380</ymin>
			<xmax>576</xmax>
			<ymax>387</ymax>
		</box>
	</object>
	<object>
		<name>WOOD</name>
		<box>
			<xmin>590</xmin>
			<ymin>380</ymin>
			<xmax>602</xmax>
			<ymax>387</ymax>
		</box>
	</object>
	<object>
		<name>ICE</name>
		<box>
			<xmin>607</xmin>
			<ymin>380</ymin>
			<xmax>619</xmax>
			<ymax>387</ymax>
		</box>
	</object>
	<object>
		<name>STONE</name>
		<box>
			<xmin>631</xmin>
			<ymin>380</ymin>
			<xmax>643</xmax>
			<ymax>387</ymax>
		</box>
	</object>
	<object>
		<name>STONE</name>
		<box>
			<xmin>657</xmin>
			<ymin>380</ymin>
			<xmax>669</xmax>
			<ymax>387</ymax>
		</box>
	</object>
	<object>
		<name>STONE</name>
		<box>
			<xmin>338</xmin>
			<ymin>368</ymin>
			<xmax>350</xmax>
			<ymax>380</ymax>
		</box>
	</object>
	<object>
		<name>STONE</name>
		<box>
			<xmin>364</xmin>
			<ymin>368</ymin>
			<xmax>376</xmax>
			<ymax>380</ymax>
		</box>
	</object>
	<object>
		<name>STONE</name>
		<box>
			<xmin>390</xmin>
			<ymin>368</ymin>
			<xmax>402</xmax>
			<ymax>380</ymax>
		</box>
	</object>
	<object>
		<name>ICE</name>
		<box>
			<xmin>405</xmin>
			<ymin>368</ymin>
			<xmax>417</xmax>
			<ymax>380</ymax>
		</box>
	</object>
	<object>
		<name>WOOD</name>
		<box>
			<xmin>431</xmin>
			<ymin>368</ymin>
			<xmax>443</xmax>
			<ymax>380</ymax>
		</box>
	</object>
	<object>
		<name>WOOD</name>
		<box>
			<xmin>457</xmin>
			<ymin>368</ymin>
			<xmax>469</xmax>
			<ymax>380</ymax>
		</box>
	</object>
	<object>
		<name>STONE</name>
		<box>
			<xmin>472</xmin>
			<ymin>368</ymin>
			<xmax>484</xmax>
			<ymax>380</ymax>
		</box>
	</object>
	<object>
		<name>STONE</name>
		<box>
			<xmin>497</xmin>
			<ymin>368</ymin>
			<xmax>510</xmax>
			<ymax>380</ymax>
		</box>
	</object>
	<object>
		<name>STONE</name>
		<box>
			<xmin>523</xmin>
			<ymin>368</ymin>
			<xmax>535</xmax>
			<ymax>380</ymax>
		</box>
	</object>
	<object>
		<name>WOOD</name>
		<box>
			<xmin>538</xmin>
			<ymin>368</ymin>
			<xmax>550</xmax>
			<ymax>380</ymax>
		</box>
	</object>
	<object>
		<name>ICE</name>
		<box>
			<xmin>564</xmin>
			<ymin>368</ymin>
			<xmax>576</xmax>
			<ymax>380</ymax>
		</box>
	</object>
	<object>
		<name>WOOD</name>
		<box>
			<xmin>590</xmin>
			<ymin>368</ymin>
			<xmax>602</xmax>
			<ymax>380</ymax>
		</box>
	</object>
	<object>
		<name>STONE</name>
		<box>
			<xmin>605</xmin>
			<ymin>368</ymin>
			<xmax>617</xmax>
			<ymax>380</ymax>
		</box>
	</object>
	<object>
		<name>STONE</name>
		<box>
			<xmin>631</xmin>
			<ymin>368</ymin>
			<xmax>643</xmax>
			<ymax>380</ymax>
		</box>
	</object>
	<object>
		<name>STONE</name>
		<box>
			<xmin>657</xmin>
			<ymin>368</ymin>
			<xmax>669</xmax>
			<ymax>380</ymax>
		</box>
	</object>
	<object>
		<name>STONE</name>
		<box>
			<xmin>338</xmin>
			<ymin>355</ymin>
			<xmax>350</xmax>
			<ymax>367</ymax>
		</box>
	</object>
	<object>
		<name>STONE</name>
		<box>
			<xmin>364</xmin>
			<ymin>355</ymin>
			<xmax>376</xmax>
			<ymax>368</ymax>
		</box>
	</object>
	<object>
		<name>WOOD</name>
		<box>
			<xmin>390</xmin>
			<ymin>355</ymin>
			<xmax>402</xmax>
			<ymax>368</ymax>
		</box>
	</object>
	<object>
		<name>WOOD</name>
		<box>
			<xmin>405</xmin>
			<ymin>355</ymin>
			<xmax>417</xmax>
			<ymax>368</ymax>
		</box>
	</object>
	<object>
		<name>WOOD</name>
		<box>
			<xmin>431</xmin>
			<ymin>355</ymin>
			<xmax>443</xmax>
			<ymax>368</ymax>
		</box>
	</object>
	<object>
		<name>WOOD</name>
		<box>
			<xmin>457</xmin>
			<ymin>356</ymin>
			<xmax>469</xmax>
			<ymax>368</ymax>
		</box>
	</object>
	<object>
		<name>ICE</name>
		<box>
			<xmin>472</xmin>
			<ymin>356</ymin>
			<xmax>484</xmax>
			<ymax>368</ymax>
		</box>
	</object>
	<object>
		<name>STONE</name>
		<box>
			<xmin>497</xmin>
			<ymin>355</ymin>
			<xmax>510</xmax>
			<ymax>368</ymax>
		</box>
	</object>
	<object>
		<name>WOOD</name>
		<box>
			<xmin>523</xmin>
			<ymin>355</ymin>
			<xmax>535</xmax>
			<ymax>367</ymax>
		</box>
	</object>
	<object>
		<name>WOOD</name>
		<box>
			<xmin>538</xmin>
			<ymin>356</ymin>
			<xmax>550</xmax>
			<ymax>368</ymax>
		</box>
	</object>
	<object>
		<name>WOOD</name>
		<box>
			<xmin>564</xmin>
			<ymin>356</ymin>
			<xmax>576</xmax>
			<ymax>368</ymax>
		</box>
	</object>
	<object>
		<name>WOOD</name>
		<box>
			<xmin>590</xmin>
			<ymin>356</ymin>
			<xmax>602</xmax>
			<ymax>368</ymax>
		</box>
	</object>
	<object>
		<name>WOOD</name>
		<box>
			<xmin>605</xmin>
			<ymin>356</ymin>
			<xmax>617</xmax>
			<ymax>368</ymax>
		</box>
	</object>
	<object>
		<name>STONE</name>
		<box>
			<xmin>631</xmin>
			<ymin>356</ymin>
			<xmax>643</xmax>
			<ymax>368</ymax>
		</box>
	</object>
	<object>
		<name>STONE</name>
		<box>
			<xmin>657</xmin>
			<ymin>355</ymin>
			<xmax>669</xmax>
			<ymax>367</ymax>
		</box>
	</object>
	<object>
		<name>WOOD</name>
		<box>
			<xmin>338</xmin>
			<ymin>343</ymin>
			<xmax>350</xmax>
			<ymax>355</ymax>
		</box>
	</object>
	<object>
		<name>WOOD</name>
		<box>
			<xmin>364</xmin>
			<ymin>343</ymin>
			<xmax>376</xmax>
			<ymax>355</ymax>
		</box>
	</object>
	<object>
		<name>ICE</name>
		<box>
			<xmin>390</xmin>
			<ymin>343</ymin>
			<xmax>402</xmax>
			<ymax>355</ymax>
		</box>
	</object>
	<object>
		<name>ICE</name>
		<box>
			<xmin>405</xmin>
			<ymin>343</ymin>
			<xmax>417</xmax>
			<ymax>355</ymax>
		</box>
	</object>
	<object>
		<name>WOOD</name>
		<box>
			<xmin>431</xmin>
			<ymin>343</ymin>
			<xmax>443</xmax>
			<ymax>355</ymax>
		</box>
	</object>
	<object>
		<name>STONE</name>
		<box>
			<xmin>457</xmin>
			<ymin>343</ymin>
			<xmax>469</xmax>
			<ymax>355</ymax>
		</box>
	</object>
	<object>
		<name>STONE</name>
		<box>
			<xmin>472</xmin>
			<ymin>343</ymin>
			<xmax>484</xmax>
			<ymax>355</ymax>
		</box>
	</object>
	<object>
		<name>WOOD</name>
		<box>
			<xmin>498</xmin>
			<ymin>343</ymin>
			<xmax>510</xmax>
			<ymax>355</ymax>
		</box>
	</object>
	<object>
		<name>WOOD</name>
		<box>
			<xmin>523</xmin>
			<ymin>343</ymin>
			<xmax>535</xmax>
			<ymax>355</ymax>
		</box>
	</object>
	<object>
		<name>WOOD</name>
		<box>
			<xmin>538</xmin>
			<ymin>343</ymin>
			<xmax>550</xmax>
			<ymax>355</ymax>
		</box>
	</object>
	<object>
		<name>WOOD</name>
		<box>
			<xmin>564</xmin>
			<ymin>343</ymin>
			<xmax>576</xmax>
			<ymax>355</ymax>
		</box>
	</object>
	<object>
		<name>ICE</name>
		<box>
			<xmin>590</xmin>
			<ymin>343</ymin>
			<xmax>602</xmax>
			<ymax>355</ymax>
		</box>
	</object>
	<object>
		<name>STONE</name>
		<box>
			<xmin>605</xmin>
			<ymin>343</ymin>
			<xmax>617</xmax>
			<ymax>356</ymax>
		</box>
	</object>
	<object>
		<name>STONE</name>
		<box>
			<xmin>631</xmin>
			<ymin>343</ymin>
			<xmax>643</xmax>
			<ymax>355</ymax>
		</box>
	</object>
	<object>
		<name>STONE</name>
		<box>
			<xmin>657</xmin>
			<ymin>343</ymin>
			<xmax>669</xmax>
			<ymax>355</ymax>
		</box>
	</object>
	<object>
		<name>WOOD</name>
		<box>
			<xmin>338</xmin>
			<ymin>331</ymin>
			<xmax>350</xmax>
			<ymax>343</ymax>
		</box>
	</object>
	<object>
		<name>WOOD</name>
		<box>
			<xmin>364</xmin>
			<ymin>331</ymin>
			<xmax>376</xmax>
			<ymax>343</ymax>
		</box>
	</object>
	<object>
		<name>ICE</name>
		<box>
			<xmin>390</xmin>
			<ymin>331</ymin>
			<xmax>402</xmax>
			<ymax>343</ymax>
		</box>
	</object>
	<object>
		<name>ICE</name>
		<box>
			<xmin>405</xmin>
			<ymin>331</ymin>
			<xmax>417</xmax>
			<ymax>343</ymax>
		</box>
	</object>
	<object>
		<name>ICE</name>
		<box>
			<xmin>431</xmin>
			<ymin>331</ymin>
			<xmax>443</xmax>
			<ymax>343</ymax>
		</box>
	</object>
	<object>
		<name>ICE</name>
		<box>
			<xmin>457</xmin>
			<ymin>331</ymin>
			<xmax>469</xmax>
			<ymax>343</ymax>
		</box>
	</object>
	<object>
		<name>STONE</name>
		<box>
			<xmin>472</xmin>
			<ymin>331</ymin>
			<xmax>484</xmax>
			<ymax>343</ymax>
		</box>
	</object>
	<object>
		<name>STONE</name>
		<box>
			<xmin>497</xmin>
			<ymin>331</ymin>
			<xmax>510</xmax>
			<ymax>343</ymax>
		</box>
	</object>
	<object>
		<name>ICE</name>
		<box>
			<xmin>523</xmin>
			<ymin>331</ymin>
			<xmax>535</xmax>
			<ymax>343</ymax>
		</box>
	</object>
	<object>
		<name>STONE</name>
		<box>
			<xmin>538</xmin>
			<ymin>331</ymin>
			<xmax>550</xmax>
			<ymax>343</ymax>
		</box>
	</object>
	<object>
		<name>ICE</name>
		<box>
			<xmin>564</xmin>
			<ymin>331</ymin>
			<xmax>576</xmax>
			<ymax>343</ymax>
		</box>
	</object>
	<object>
		<name>STONE</name>
		<box>
			<xmin>590</xmin>
			<ymin>331</ymin>
			<xmax>602</xmax>
			<ymax>343</ymax>
		</box>
	</object>
	<object>
		<name>STONE</name>
		<box>
			<xmin>605</xmin>
			<ymin>331</ymin>
			<xmax>617</xmax>
			<ymax>343</ymax>
		</box>
	</object>
	<object>
		<name>STONE</name>
		<box>
			<xmin>631</xmin>
			<ymin>331</ymin>
			<xmax>643</xmax>
			<ymax>343</ymax>
		</box>
	</object>
	<object>
		<name>STONE</name>
		<box>
			<xmin>657</xmin>
			<ymin>331</ymin>
			<xmax>669</xmax>
			<ymax>343</ymax>
		</box>
	</object>
	<object>
		<name>WOOD</name>
		<box>
			<xmin>338</xmin>
			<ymin>306</ymin>
			<xmax>350</xmax>
			<ymax>330</ymax>
		</box>
	</object>
	<object>
		<name>WOOD</name>
		<box>
			<xmin>364</xmin>
			<ymin>306</ymin>
			<xmax>376</xmax>
			<ymax>330</ymax>
		</box>
	</object>
	<object>
		<name>ICE</name>
		<box>
			<xmin>390</xmin>
			<ymin>306</ymin>
			<xmax>402</xmax>
			<ymax>330</ymax>
		</box>
	</object>
	<object>
		<name>ICE</name>
		<box>
			<xmin>408</xmin>
			<ymin>306</ymin>
			<xmax>414</xmax>
			<ymax>330</ymax>
		</box>
	</object>
	<object>
		<name>ICE</name>
		<box>
			<xmin>433</xmin>
			<ymin>306</ymin>
			<xmax>440</xmax>
			<ymax>330</ymax>
		</box>
	</object>
	<object>
		<name>ICE</name>
		<box>
			<xmin>459</xmin>
			<ymin>306</ymin>
			<xmax>466</xmax>
			<ymax>330</ymax>
		</box>
	</object>
	<object>
		<name>ICE</name>
		<box>
			<xmin>472</xmin>
			<ymin>306</ymin>
			<xmax>484</xmax>
			<ymax>330</ymax>
		</box>
	</object>
	<object>
		<name>ICE</name>
		<box>
			<xmin>497</xmin>
			<ymin>306</ymin>
			<xmax>510</xmax>
			<ymax>330</ymax>
		</box>
	</object>
	<object>
		<name>ICE</name>
		<box>
			<xmin>523</xmin>
			<ymin>306</ymin>
			<xmax>535</xmax>
			<ymax>330</ymax>
		</box>
	</object>
	<object>
		<name>STONE</name>
		<box>
			<xmin>541</xmin>
			<ymin>307</ymin>
			<xmax>547</xmax>
			<ymax>330</ymax>
		</box>
	</object>
	<object>
		<name>ICE</name>
		<box>
			<xmin>567</xmin>
			<ymin>307</ymin>
			<xmax>573</xmax>
			<ymax>330</ymax>
		</box>
	</object>
	<object>
		<name>STONE</name>
		<box>
			<xmin>590</xmin>
			<ymin>307</ymin>
			<xmax>602</xmax>
			<ymax>330</ymax>
		</box>
	</object>
	<object>
		<name>STONE</name>
		<box>
			<xmin>605</xmin>
			<ymin>307</ymin>
			<xmax>617</xmax>
			<ymax>331</ymax>
		</box>
	</object>
	<object>
		<name>ICE</name>
		<box>
			<xmin>634</xmin>
			<ymin>306</ymin>
			<xmax>641</xmax>
			<ymax>330</ymax>
		</box>
	</object>
	<object>
		<name>WOOD</name>
		<box>
			<xmin>659</xmin>
			<ymin>306</ymin>
			<xmax>666</xmax>
			<ymax>330</ymax>
		</box>
	</object>
	<object>
		<name>STONE</name>
		<box>
			<xmin>341</xmin>
			<ymin>300</ymin>
			<xmax>399</xmax>
			<ymax>306</ymax>
		</box>
	</object>
	<object>
		<name>WOOD</name>
		<box>
			<xmin>408</xmin>
			<ymin>300</ymin>
			<xmax>466</xmax>
			<ymax>306</ymax>
		</box>
	</object>
	<object>
		<name>WOOD</name>
		<box>
			<xmin>475</xmin>
			<ymin>300</ymin>
			<xmax>532</xmax>
			<ymax>306</ymax>
		</box>
	</object>
	<object>
		<name>WOOD</name>
		<box>
			<xmin>541</xmin>
			<ymin>300</ymin>
			<xmax>599</xmax>
			<ymax>306</ymax>
		</box>
	</object>
	<object>
		<name>STONE</name>
		<box>
			<xmin>608</xmin>
			<ymin>300</ymin>
			<xmax>666</xmax>
			<ymax>306</ymax>
		</box>
	</object>
	<object>
		<name>WOOD</name>
		<box>
			<xmin>341</xmin>
			<ymin>293</ymin>
			<xmax>399</xmax>
			<ymax>299</ymax>
		</box>
	</object>
	<object>
		<name>WOOD</name>
		<box>
			<xmin>434</xmin>
			<ymin>294</ymin>
			<xmax>440</xmax>
			<ymax>299</ymax>
		</box>
	</object>
	<object>
		<name>WOOD</name>
		<box>
			<xmin>492</xmin>
			<ymin>293</ymin>
			<xmax>515</xmax>
			<ymax>299</ymax>
		</box>
	</object>
	<object>
		<name>WOOD</name>
		<box>
			<xmin>564</xmin>
			<ymin>293</ymin>
			<xmax>576</xmax>
			<ymax>300</ymax>
		</box>
	</object>
	<object>
		<name>STONE</name>
		<box>
			<xmin>608</xmin>
			<ymin>293</ymin>
			<xmax>666</xmax>
			<ymax>300</ymax>
		</box>
	</object>
	<object>
		<name>STONE</name>
		<box>
			<xmin>395</xmin>
			<ymin>237</ymin>
			<xmax>408</xmax>
			<ymax>243</ymax>
		</box>
	</object>
	<object>
		<name>ICE</name>
		<box>
			<xmin>413</xmin>
			<ymin>237</ymin>
			<xmax>425</xmax>
			<ymax>243</ymax>
		</box>
	</object>
	<object>
		<name>WOOD</name>
		<box>
			<xmin>432</xmin>
			<ymin>237</ymin>
			<xmax>444</xmax>
			<ymax>243</ymax>
		</box>
	</object>
	<object>
		<name>WOOD</name>
		<box>
			<xmin>449</xmin>
			<ymin>237</ymin>
			<xmax>461</xmax>
			<ymax>243</ymax>
		</box>
	</object>
	<object>
		<name>ICE</name>
		<box>
			<xmin>468</xmin>
			<ymin>237</ymin>
			<xmax>480</xmax>
			<ymax>243</ymax>
		</box>
	</object>
	<object>
		<name>WOOD</name>
		<box>
			<xmin>486</xmin>
			<ymin>237</ymin>
			<xmax>498</xmax>
			<ymax>243</ymax>
		</box>
	</object>
	<object>
		<name>STONE</name>
		<box>
			<xmin>395</xmin>
			<ymin>230</ymin>
			<xmax>407</xmax>
			<ymax>237</ymax>
		</box>
	</object>
	<object>
		<name>ICE</name>
		<box>
			<xmin>413</xmin>
			<ymin>231</ymin>
			<xmax>425</xmax>
			<ymax>237</ymax>
		</box>
	</object>
	<object>
		<name>STONE</name>
		<box>
			<xmin>431</xmin>
			<ymin>231</ymin>
			<xmax>444</xmax>
			<ymax>237</ymax>
		</box>
	</object>
	<object>
		<name>WOOD</name>
		<box>
			<xmin>449</xmin>
			<ymin>231</ymin>
			<xmax>461</xmax>
			<ymax>237</ymax>
		</box>
	</object>
	<object>
		<name>ICE</name>
		<box>
			<xmin>468</xmin>
			<ymin>231</ymin>
			<xmax>480</xmax>
			<ymax>237</ymax>
		</box>
	</object>
	<object>
		<name>WOOD</name>
		<box>
			<xmin>486</xmin>
			<ymin>231</ymin>
			<xmax>498</xmax>
			<ymax>237</ymax>
		</box>
	</object>
	<object>
		<name>STONE</name>
		<box>
			<xmin>398</xmin>
			<ymin>224</ymin>
			<xmax>422</xmax>
			<ymax>230</ymax>
		</box>
	</object>
	<object>
		<name>WOOD</name>
		<box>
			<xmin>434</xmin>
			<ymin>224</ymin>
			<xmax>458</xmax>
			<ymax>231</ymax>
		</box>
	</object>
	<object>
		<name>WOOD</name>
		<box>
			<xmin>471</xmin>
			<ymin>224</ymin>
			<xmax>494</xmax>
			<ymax>231</ymax>
		</box>
	</object>
	<object>
		<name>STONE</name>
		<box>
			<xmin>398</xmin>
			<ymin>200</ymin>
			<xmax>405</xmax>
			<ymax>224</ymax>
		</box>
	</object>
	<object>
		<name>STONE</name>
		<box>
			<xmin>416</xmin>
			<ymin>200</ymin>
			<xmax>422</xmax>
			<ymax>224</ymax>
		</box>
	</object>
	<object>
		<name>STONE</name>
		<box>
			<xmin>435</xmin>
			<ymin>200</ymin>
			<xmax>441</xmax>
			<ymax>224</ymax>
		</box>
	</object>
	<object>
		<name>STONE</name>
		<box>
			<xmin>452</xmin>
			<ymin>200</ymin>
			<xmax>458</xmax>
			<ymax>224</ymax>
		</box>
	</object>
	<object>
		<name>STONE</name>
		<box>
			<xmin>471</xmin>
			<ymin>200</ymin>
			<xmax>477</xmax>
			<ymax>224</ymax>
		</box>
	</object>
	<object>
		<name>STONE</name>
		<box>
			<xmin>488</xmin>
			<ymin>200</ymin>
			<xmax>494</xmax>
			<ymax>224</ymax>
		</box>
	</object>
	<object>
		<name>WOOD</name>
		<box>
			<xmin>443</xmin>
			<ymin>153</ymin>
			<xmax>466</xmax>
			<ymax>176</ymax>
		</box>
	</object>
	<object>
		<name>WOOD</name>
		<box>
			<xmin>625</xmin>
			<ymin>269</ymin>
			<xmax>648</xmax>
			<ymax>293</ymax>
		</box>
	</object>
	<object>
		<name>WOOD</name>
		<box>
			<xmin>406</xmin>
			<ymin>276</ymin>
			<xmax>429</xmax>
			<ymax>299</ymax>
		</box>
	</object>
	<object>
		<name>STONE</name>
		<box>
			<xmin>444</xmin>
			<ymin>276</ymin>
			<xmax>468</xmax>
			<ymax>299</ymax>
		</box>
	</object>
	<object>
		<name>WOOD</name>
		<box>
			<xmin>398</xmin>
			<ymin>176</ymin>
			<xmax>422</xmax>
			<ymax>200</ymax>
		</box>
	</object>
	<object>
		<name>WOOD</name>
		<box>
			<xmin>435</xmin>
			<ymin>176</ymin>
			<xmax>458</xmax>
			<ymax>200</ymax>
		</box>
	</object>
	<object>
		<name>STONE</name>
		<box>
			<xmin>471</xmin>
			<ymin>176</ymin>
			<xmax>494</xmax>
			<ymax>200</ymax>
		</box>
	</object>
	<object>
		<name>PIG</name>
		<box>
			<xmin>384</xmin>
			<ymin>282</ymin>
			<xmax>396</xmax>
			<ymax>292</ymax>
		</box>
	</object>
	<object>
		<name>PIG</name>
		<box>
			<xmin>498</xmin>
			<ymin>282</ymin>
			<xmax>510</xmax>
			<ymax>292</ymax>
		</box>
	</object>
	<object>
		<name>PIG</name>
		<box>
			<xmin>650</xmin>
			<ymin>282</ymin>
			<xmax>663</xmax>
			<ymax>292</ymax>
		</box>
	</object>
	<object>
		<name>PIG</name>
		<box>
			<xmin>397</xmin>
			<ymin>164</ymin>
			<xmax>410</xmax>
			<ymax>175</ymax>
		</box>
	</object>
	<object>
		<name>PIG</name>
		<box>
			<xmin>484</xmin>
			<ymin>165</ymin>
			<xmax>497</xmax>
			<ymax>175</ymax>
		</box>
	</object>
	<object>
		<name>PIG</name>
		<box>
			<xmin>612</xmin>
			<ymin>282</ymin>
			<xmax>624</xmax>
			<ymax>293</ymax>
		</box>
	</object>
	<object>
		<name>PIG</name>
		<box>
			<xmin>345</xmin>
			<ymin>282</ymin>
			<xmax>358</xmax>
			<ymax>292</ymax>
		</box>
	</object>
</annotation>
