<?xml version="1.0" encoding="UTF-8"?>
<annotation>
	<filename>dataset/annotations/4275.xml</filename>
	<objects>130</objects>
	<object>
		<name>REDBIRD</name>
		<box>
			<xmin>186</xmin>
			<ymin>338</ymin>
			<xmax>198</xmax>
			<ymax>349</ymax>
		</box>
	</object>
	<object>
		<name>BLUEBIRD</name>
		<box>
			<xmin>167</xmin>
			<ymin>383</ymin>
			<xmax>175</xmax>
			<ymax>391</ymax>
		</box>
	</object>
	<object>
		<name>YELLOWBIRD</name>
		<box>
			<xmin>131</xmin>
			<ymin>377</ymin>
			<xmax>147</xmax>
			<ymax>392</ymax>
		</box>
	</object>
	<object>
		<name>BLACKBIRD</name>
		<box>
			<xmin>90</xmin>
			<ymin>370</ymin>
			<xmax>108</xmax>
			<ymax>394</ymax>
		</box>
	</object>
	<object>
		<name>REDBIRD</name>
		<box>
			<xmin>100</xmin>
			<ymin>382</ymin>
			<xmax>112</xmax>
			<ymax>393</ymax>
		</box>
	</object>
	<object>
		<name>SLING</name>
		<box>
			<xmin>182</xmin>
			<ymin>337</ymin>
			<xmax>202</xmax>
			<ymax>394</ymax>
		</box>
	</object>
	<object>
		<name>UNKNOWN</name>
		<box>
			<xmin>377</xmin>
			<ymin>394</ymin>
			<xmax>395</xmax>
			<ymax>395</ymax>
		</box>
	</object>
	<object>
		<name>UNKNOWN</name>
		<box>
			<xmin>395</xmin>
			<ymin>394</ymin>
			<xmax>413</xmax>
			<ymax>395</ymax>
		</box>
	</object>
	<object>
		<name>UNKNOWN</name>
		<box>
			<xmin>360</xmin>
			<ymin>394</ymin>
			<xmax>378</xmax>
			<ymax>395</ymax>
		</box>
	</object>
	<object>
		<name>UNKNOWN</name>
		<box>
			<xmin>412</xmin>
			<ymin>394</ymin>
			<xmax>430</xmax>
			<ymax>395</ymax>
		</box>
	</object>
	<object>
		<name>UNKNOWN</name>
		<box>
			<xmin>343</xmin>
			<ymin>394</ymin>
			<xmax>361</xmax>
			<ymax>395</ymax>
		</box>
	</object>
	<object>
		<name>HILL</name>
		<box>
			<xmin>482</xmin>
			<ymin>389</ymin>
			<xmax>500</xmax>
			<ymax>395</ymax>
		</box>
	</object>
	<object>
		<name>HILL</name>
		<box>
			<xmin>499</xmin>
			<ymin>389</ymin>
			<xmax>517</xmax>
			<ymax>395</ymax>
		</box>
	</object>
	<object>
		<name>HILL</name>
		<box>
			<xmin>465</xmin>
			<ymin>389</ymin>
			<xmax>482</xmax>
			<ymax>395</ymax>
		</box>
	</object>
	<object>
		<name>HILL</name>
		<box>
			<xmin>511</xmin>
			<ymin>389</ymin>
			<xmax>529</xmax>
			<ymax>395</ymax>
		</box>
	</object>
	<object>
		<name>HILL</name>
		<box>
			<xmin>453</xmin>
			<ymin>389</ymin>
			<xmax>471</xmax>
			<ymax>395</ymax>
		</box>
	</object>
	<object>
		<name>HILL</name>
		<box>
			<xmin>599</xmin>
			<ymin>375</ymin>
			<xmax>617</xmax>
			<ymax>393</ymax>
		</box>
	</object>
	<object>
		<name>HILL</name>
		<box>
			<xmin>599</xmin>
			<ymin>393</ymin>
			<xmax>617</xmax>
			<ymax>395</ymax>
		</box>
	</object>
	<object>
		<name>HILL</name>
		<box>
			<xmin>617</xmin>
			<ymin>375</ymin>
			<xmax>634</xmax>
			<ymax>393</ymax>
		</box>
	</object>
	<object>
		<name>HILL</name>
		<box>
			<xmin>582</xmin>
			<ymin>375</ymin>
			<xmax>600</xmax>
			<ymax>393</ymax>
		</box>
	</object>
	<object>
		<name>UNKNOWN</name>
		<box>
			<xmin>617</xmin>
			<ymin>393</ymin>
			<xmax>634</xmax>
			<ymax>395</ymax>
		</box>
	</object>
	<object>
		<name>HILL</name>
		<box>
			<xmin>582</xmin>
			<ymin>393</ymin>
			<xmax>600</xmax>
			<ymax>395</ymax>
		</box>
	</object>
	<object>
		<name>HILL</name>
		<box>
			<xmin>634</xmin>
			<ymin>375</ymin>
			<xmax>652</xmax>
			<ymax>393</ymax>
		</box>
	</object>
	<object>
		<name>HILL</name>
		<box>
			<xmin>564</xmin>
			<ymin>375</ymin>
			<xmax>582</xmax>
			<ymax>393</ymax>
		</box>
	</object>
	<object>
		<name>HILL</name>
		<box>
			<xmin>634</xmin>
			<ymin>393</ymin>
			<xmax>652</xmax>
			<ymax>395</ymax>
		</box>
	</object>
	<object>
		<name>UNKNOWN</name>
		<box>
			<xmin>564</xmin>
			<ymin>393</ymin>
			<xmax>582</xmax>
			<ymax>395</ymax>
		</box>
	</object>
	<object>
		<name>HILL</name>
		<box>
			<xmin>647</xmin>
			<ymin>375</ymin>
			<xmax>665</xmax>
			<ymax>393</ymax>
		</box>
	</object>
	<object>
		<name>HILL</name>
		<box>
			<xmin>552</xmin>
			<ymin>375</ymin>
			<xmax>570</xmax>
			<ymax>393</ymax>
		</box>
	</object>
	<object>
		<name>HILL</name>
		<box>
			<xmin>647</xmin>
			<ymin>393</ymin>
			<xmax>665</xmax>
			<ymax>395</ymax>
		</box>
	</object>
	<object>
		<name>HILL</name>
		<box>
			<xmin>552</xmin>
			<ymin>393</ymin>
			<xmax>570</xmax>
			<ymax>395</ymax>
		</box>
	</object>
	<object>
		<name>HILL</name>
		<box>
			<xmin>429</xmin>
			<ymin>389</ymin>
			<xmax>458</xmax>
			<ymax>395</ymax>
		</box>
	</object>
	<object>
		<name>UNKNOWN</name>
		<box>
			<xmin>429</xmin>
			<ymin>394</ymin>
			<xmax>454</xmax>
			<ymax>395</ymax>
		</box>
	</object>
	<object>
		<name>HILL</name>
		<box>
			<xmin>528</xmin>
			<ymin>376</ymin>
			<xmax>561</xmax>
			<ymax>395</ymax>
		</box>
	</object>
	<object>
		<name>UNKNOWN</name>
		<box>
			<xmin>528</xmin>
			<ymin>394</ymin>
			<xmax>561</xmax>
			<ymax>395</ymax>
		</box>
	</object>
	<object>
		<name>HILL</name>
		<box>
			<xmin>526</xmin>
			<ymin>389</ymin>
			<xmax>554</xmax>
			<ymax>395</ymax>
		</box>
	</object>
	<object>
		<name>ICE</name>
		<box>
			<xmin>413</xmin>
			<ymin>264</ymin>
			<xmax>434</xmax>
			<ymax>285</ymax>
		</box>
	</object>
	<object>
		<name>WOOD</name>
		<box>
			<xmin>380</xmin>
			<ymin>273</ymin>
			<xmax>392</xmax>
			<ymax>285</ymax>
		</box>
	</object>
	<object>
		<name>STONE</name>
		<box>
			<xmin>357</xmin>
			<ymin>264</ymin>
			<xmax>378</xmax>
			<ymax>285</ymax>
		</box>
	</object>
	<object>
		<name>ICE</name>
		<box>
			<xmin>627</xmin>
			<ymin>254</ymin>
			<xmax>638</xmax>
			<ymax>265</ymax>
		</box>
	</object>
	<object>
		<name>WOOD</name>
		<box>
			<xmin>578</xmin>
			<ymin>253</ymin>
			<xmax>589</xmax>
			<ymax>265</ymax>
		</box>
	</object>
	<object>
		<name>WOOD</name>
		<box>
			<xmin>594</xmin>
			<ymin>253</ymin>
			<xmax>606</xmax>
			<ymax>265</ymax>
		</box>
	</object>
	<object>
		<name>STONE</name>
		<box>
			<xmin>343</xmin>
			<ymin>370</ymin>
			<xmax>355</xmax>
			<ymax>394</ymax>
		</box>
	</object>
	<object>
		<name>STONE</name>
		<box>
			<xmin>362</xmin>
			<ymin>370</ymin>
			<xmax>374</xmax>
			<ymax>394</ymax>
		</box>
	</object>
	<object>
		<name>WOOD</name>
		<box>
			<xmin>380</xmin>
			<ymin>370</ymin>
			<xmax>392</xmax>
			<ymax>394</ymax>
		</box>
	</object>
	<object>
		<name>WOOD</name>
		<box>
			<xmin>399</xmin>
			<ymin>370</ymin>
			<xmax>411</xmax>
			<ymax>394</ymax>
		</box>
	</object>
	<object>
		<name>WOOD</name>
		<box>
			<xmin>417</xmin>
			<ymin>370</ymin>
			<xmax>429</xmax>
			<ymax>394</ymax>
		</box>
	</object>
	<object>
		<name>STONE</name>
		<box>
			<xmin>343</xmin>
			<ymin>358</ymin>
			<xmax>355</xmax>
			<ymax>370</ymax>
		</box>
	</object>
	<object>
		<name>STONE</name>
		<box>
			<xmin>362</xmin>
			<ymin>358</ymin>
			<xmax>374</xmax>
			<ymax>370</ymax>
		</box>
	</object>
	<object>
		<name>WOOD</name>
		<box>
			<xmin>380</xmin>
			<ymin>358</ymin>
			<xmax>392</xmax>
			<ymax>370</ymax>
		</box>
	</object>
	<object>
		<name>WOOD</name>
		<box>
			<xmin>399</xmin>
			<ymin>358</ymin>
			<xmax>411</xmax>
			<ymax>370</ymax>
		</box>
	</object>
	<object>
		<name>WOOD</name>
		<box>
			<xmin>417</xmin>
			<ymin>358</ymin>
			<xmax>429</xmax>
			<ymax>370</ymax>
		</box>
	</object>
	<object>
		<name>STONE</name>
		<box>
			<xmin>343</xmin>
			<ymin>333</ymin>
			<xmax>355</xmax>
			<ymax>357</ymax>
		</box>
	</object>
	<object>
		<name>WOOD</name>
		<box>
			<xmin>362</xmin>
			<ymin>334</ymin>
			<xmax>374</xmax>
			<ymax>357</ymax>
		</box>
	</object>
	<object>
		<name>WOOD</name>
		<box>
			<xmin>380</xmin>
			<ymin>334</ymin>
			<xmax>392</xmax>
			<ymax>358</ymax>
		</box>
	</object>
	<object>
		<name>WOOD</name>
		<box>
			<xmin>399</xmin>
			<ymin>333</ymin>
			<xmax>411</xmax>
			<ymax>357</ymax>
		</box>
	</object>
	<object>
		<name>WOOD</name>
		<box>
			<xmin>417</xmin>
			<ymin>334</ymin>
			<xmax>429</xmax>
			<ymax>357</ymax>
		</box>
	</object>
	<object>
		<name>WOOD</name>
		<box>
			<xmin>343</xmin>
			<ymin>321</ymin>
			<xmax>355</xmax>
			<ymax>333</ymax>
		</box>
	</object>
	<object>
		<name>STONE</name>
		<box>
			<xmin>362</xmin>
			<ymin>321</ymin>
			<xmax>374</xmax>
			<ymax>333</ymax>
		</box>
	</object>
	<object>
		<name>STONE</name>
		<box>
			<xmin>380</xmin>
			<ymin>321</ymin>
			<xmax>392</xmax>
			<ymax>334</ymax>
		</box>
	</object>
	<object>
		<name>STONE</name>
		<box>
			<xmin>399</xmin>
			<ymin>321</ymin>
			<xmax>411</xmax>
			<ymax>333</ymax>
		</box>
	</object>
	<object>
		<name>WOOD</name>
		<box>
			<xmin>417</xmin>
			<ymin>321</ymin>
			<xmax>429</xmax>
			<ymax>333</ymax>
		</box>
	</object>
	<object>
		<name>ICE</name>
		<box>
			<xmin>343</xmin>
			<ymin>297</ymin>
			<xmax>355</xmax>
			<ymax>321</ymax>
		</box>
	</object>
	<object>
		<name>ICE</name>
		<box>
			<xmin>362</xmin>
			<ymin>297</ymin>
			<xmax>374</xmax>
			<ymax>321</ymax>
		</box>
	</object>
	<object>
		<name>ICE</name>
		<box>
			<xmin>380</xmin>
			<ymin>297</ymin>
			<xmax>392</xmax>
			<ymax>321</ymax>
		</box>
	</object>
	<object>
		<name>ICE</name>
		<box>
			<xmin>399</xmin>
			<ymin>297</ymin>
			<xmax>411</xmax>
			<ymax>321</ymax>
		</box>
	</object>
	<object>
		<name>ICE</name>
		<box>
			<xmin>417</xmin>
			<ymin>297</ymin>
			<xmax>429</xmax>
			<ymax>321</ymax>
		</box>
	</object>
	<object>
		<name>WOOD</name>
		<box>
			<xmin>346</xmin>
			<ymin>291</ymin>
			<xmax>352</xmax>
			<ymax>297</ymax>
		</box>
	</object>
	<object>
		<name>STONE</name>
		<box>
			<xmin>365</xmin>
			<ymin>291</ymin>
			<xmax>371</xmax>
			<ymax>297</ymax>
		</box>
	</object>
	<object>
		<name>WOOD</name>
		<box>
			<xmin>380</xmin>
			<ymin>291</ymin>
			<xmax>392</xmax>
			<ymax>297</ymax>
		</box>
	</object>
	<object>
		<name>ICE</name>
		<box>
			<xmin>399</xmin>
			<ymin>290</ymin>
			<xmax>411</xmax>
			<ymax>297</ymax>
		</box>
	</object>
	<object>
		<name>WOOD</name>
		<box>
			<xmin>420</xmin>
			<ymin>291</ymin>
			<xmax>426</xmax>
			<ymax>297</ymax>
		</box>
	</object>
	<object>
		<name>WOOD</name>
		<box>
			<xmin>346</xmin>
			<ymin>285</ymin>
			<xmax>352</xmax>
			<ymax>291</ymax>
		</box>
	</object>
	<object>
		<name>WOOD</name>
		<box>
			<xmin>365</xmin>
			<ymin>285</ymin>
			<xmax>371</xmax>
			<ymax>291</ymax>
		</box>
	</object>
	<object>
		<name>WOOD</name>
		<box>
			<xmin>383</xmin>
			<ymin>285</ymin>
			<xmax>389</xmax>
			<ymax>291</ymax>
		</box>
	</object>
	<object>
		<name>ICE</name>
		<box>
			<xmin>399</xmin>
			<ymin>284</ymin>
			<xmax>411</xmax>
			<ymax>290</ymax>
		</box>
	</object>
	<object>
		<name>ICE</name>
		<box>
			<xmin>420</xmin>
			<ymin>285</ymin>
			<xmax>426</xmax>
			<ymax>291</ymax>
		</box>
	</object>
	<object>
		<name>ICE</name>
		<box>
			<xmin>453</xmin>
			<ymin>382</ymin>
			<xmax>477</xmax>
			<ymax>388</ymax>
		</box>
	</object>
	<object>
		<name>ICE</name>
		<box>
			<xmin>479</xmin>
			<ymin>382</ymin>
			<xmax>503</xmax>
			<ymax>388</ymax>
		</box>
	</object>
	<object>
		<name>ICE</name>
		<box>
			<xmin>505</xmin>
			<ymin>382</ymin>
			<xmax>529</xmax>
			<ymax>388</ymax>
		</box>
	</object>
	<object>
		<name>ICE</name>
		<box>
			<xmin>462</xmin>
			<ymin>376</ymin>
			<xmax>520</xmax>
			<ymax>382</ymax>
		</box>
	</object>
	<object>
		<name>WOOD</name>
		<box>
			<xmin>464</xmin>
			<ymin>352</ymin>
			<xmax>477</xmax>
			<ymax>375</ymax>
		</box>
	</object>
	<object>
		<name>ICE</name>
		<box>
			<xmin>505</xmin>
			<ymin>352</ymin>
			<xmax>517</xmax>
			<ymax>376</ymax>
		</box>
	</object>
	<object>
		<name>ICE</name>
		<box>
			<xmin>467</xmin>
			<ymin>327</ymin>
			<xmax>473</xmax>
			<ymax>351</ymax>
		</box>
	</object>
	<object>
		<name>ICE</name>
		<box>
			<xmin>505</xmin>
			<ymin>328</ymin>
			<xmax>517</xmax>
			<ymax>351</ymax>
		</box>
	</object>
	<object>
		<name>ICE</name>
		<box>
			<xmin>467</xmin>
			<ymin>321</ymin>
			<xmax>514</xmax>
			<ymax>327</ymax>
		</box>
	</object>
	<object>
		<name>ICE</name>
		<box>
			<xmin>552</xmin>
			<ymin>363</ymin>
			<xmax>564</xmax>
			<ymax>375</ymax>
		</box>
	</object>
	<object>
		<name>ICE</name>
		<box>
			<xmin>574</xmin>
			<ymin>363</ymin>
			<xmax>586</xmax>
			<ymax>375</ymax>
		</box>
	</object>
	<object>
		<name>ICE</name>
		<box>
			<xmin>595</xmin>
			<ymin>363</ymin>
			<xmax>607</xmax>
			<ymax>375</ymax>
		</box>
	</object>
	<object>
		<name>ICE</name>
		<box>
			<xmin>610</xmin>
			<ymin>363</ymin>
			<xmax>622</xmax>
			<ymax>375</ymax>
		</box>
	</object>
	<object>
		<name>ICE</name>
		<box>
			<xmin>631</xmin>
			<ymin>363</ymin>
			<xmax>643</xmax>
			<ymax>375</ymax>
		</box>
	</object>
	<object>
		<name>ICE</name>
		<box>
			<xmin>652</xmin>
			<ymin>363</ymin>
			<xmax>664</xmax>
			<ymax>375</ymax>
		</box>
	</object>
	<object>
		<name>ICE</name>
		<box>
			<xmin>552</xmin>
			<ymin>356</ymin>
			<xmax>564</xmax>
			<ymax>363</ymax>
		</box>
	</object>
	<object>
		<name>ICE</name>
		<box>
			<xmin>573</xmin>
			<ymin>357</ymin>
			<xmax>585</xmax>
			<ymax>363</ymax>
		</box>
	</object>
	<object>
		<name>ICE</name>
		<box>
			<xmin>595</xmin>
			<ymin>356</ymin>
			<xmax>607</xmax>
			<ymax>363</ymax>
		</box>
	</object>
	<object>
		<name>ICE</name>
		<box>
			<xmin>609</xmin>
			<ymin>356</ymin>
			<xmax>621</xmax>
			<ymax>363</ymax>
		</box>
	</object>
	<object>
		<name>ICE</name>
		<box>
			<xmin>631</xmin>
			<ymin>356</ymin>
			<xmax>643</xmax>
			<ymax>363</ymax>
		</box>
	</object>
	<object>
		<name>ICE</name>
		<box>
			<xmin>652</xmin>
			<ymin>356</ymin>
			<xmax>664</xmax>
			<ymax>363</ymax>
		</box>
	</object>
	<object>
		<name>WOOD</name>
		<box>
			<xmin>552</xmin>
			<ymin>344</ymin>
			<xmax>564</xmax>
			<ymax>356</ymax>
		</box>
	</object>
	<object>
		<name>WOOD</name>
		<box>
			<xmin>573</xmin>
			<ymin>344</ymin>
			<xmax>585</xmax>
			<ymax>356</ymax>
		</box>
	</object>
	<object>
		<name>WOOD</name>
		<box>
			<xmin>595</xmin>
			<ymin>344</ymin>
			<xmax>607</xmax>
			<ymax>356</ymax>
		</box>
	</object>
	<object>
		<name>WOOD</name>
		<box>
			<xmin>609</xmin>
			<ymin>344</ymin>
			<xmax>621</xmax>
			<ymax>356</ymax>
		</box>
	</object>
	<object>
		<name>WOOD</name>
		<box>
			<xmin>631</xmin>
			<ymin>344</ymin>
			<xmax>643</xmax>
			<ymax>356</ymax>
		</box>
	</object>
	<object>
		<name>WOOD</name>
		<box>
			<xmin>652</xmin>
			<ymin>344</ymin>
			<xmax>664</xmax>
			<ymax>356</ymax>
		</box>
	</object>
	<object>
		<name>STONE</name>
		<box>
			<xmin>555</xmin>
			<ymin>338</ymin>
			<xmax>561</xmax>
			<ymax>344</ymax>
		</box>
	</object>
	<object>
		<name>STONE</name>
		<box>
			<xmin>573</xmin>
			<ymin>338</ymin>
			<xmax>585</xmax>
			<ymax>344</ymax>
		</box>
	</object>
	<object>
		<name>STONE</name>
		<box>
			<xmin>595</xmin>
			<ymin>338</ymin>
			<xmax>607</xmax>
			<ymax>344</ymax>
		</box>
	</object>
	<object>
		<name>STONE</name>
		<box>
			<xmin>609</xmin>
			<ymin>338</ymin>
			<xmax>622</xmax>
			<ymax>344</ymax>
		</box>
	</object>
	<object>
		<name>STONE</name>
		<box>
			<xmin>634</xmin>
			<ymin>338</ymin>
			<xmax>640</xmax>
			<ymax>344</ymax>
		</box>
	</object>
	<object>
		<name>STONE</name>
		<box>
			<xmin>655</xmin>
			<ymin>338</ymin>
			<xmax>661</xmax>
			<ymax>344</ymax>
		</box>
	</object>
	<object>
		<name>ICE</name>
		<box>
			<xmin>555</xmin>
			<ymin>325</ymin>
			<xmax>579</xmax>
			<ymax>337</ymax>
		</box>
	</object>
	<object>
		<name>ICE</name>
		<box>
			<xmin>580</xmin>
			<ymin>325</ymin>
			<xmax>604</xmax>
			<ymax>337</ymax>
		</box>
	</object>
	<object>
		<name>ICE</name>
		<box>
			<xmin>613</xmin>
			<ymin>325</ymin>
			<xmax>636</xmax>
			<ymax>337</ymax>
		</box>
	</object>
	<object>
		<name>ICE</name>
		<box>
			<xmin>638</xmin>
			<ymin>325</ymin>
			<xmax>661</xmax>
			<ymax>337</ymax>
		</box>
	</object>
	<object>
		<name>ICE</name>
		<box>
			<xmin>564</xmin>
			<ymin>278</ymin>
			<xmax>570</xmax>
			<ymax>325</ymax>
		</box>
	</object>
	<object>
		<name>ICE</name>
		<box>
			<xmin>581</xmin>
			<ymin>278</ymin>
			<xmax>588</xmax>
			<ymax>325</ymax>
		</box>
	</object>
	<object>
		<name>ICE</name>
		<box>
			<xmin>596</xmin>
			<ymin>278</ymin>
			<xmax>602</xmax>
			<ymax>325</ymax>
		</box>
	</object>
	<object>
		<name>ICE</name>
		<box>
			<xmin>614</xmin>
			<ymin>278</ymin>
			<xmax>620</xmax>
			<ymax>325</ymax>
		</box>
	</object>
	<object>
		<name>ICE</name>
		<box>
			<xmin>629</xmin>
			<ymin>278</ymin>
			<xmax>635</xmax>
			<ymax>325</ymax>
		</box>
	</object>
	<object>
		<name>ICE</name>
		<box>
			<xmin>646</xmin>
			<ymin>278</ymin>
			<xmax>653</xmax>
			<ymax>325</ymax>
		</box>
	</object>
	<object>
		<name>WOOD</name>
		<box>
			<xmin>564</xmin>
			<ymin>265</ymin>
			<xmax>588</xmax>
			<ymax>277</ymax>
		</box>
	</object>
	<object>
		<name>WOOD</name>
		<box>
			<xmin>596</xmin>
			<ymin>265</ymin>
			<xmax>620</xmax>
			<ymax>277</ymax>
		</box>
	</object>
	<object>
		<name>WOOD</name>
		<box>
			<xmin>629</xmin>
			<ymin>265</ymin>
			<xmax>653</xmax>
			<ymax>278</ymax>
		</box>
	</object>
	<object>
		<name>STONE</name>
		<box>
			<xmin>495</xmin>
			<ymin>297</ymin>
			<xmax>518</xmax>
			<ymax>321</ymax>
		</box>
	</object>
	<object>
		<name>PIG</name>
		<box>
			<xmin>485</xmin>
			<ymin>364</ymin>
			<xmax>498</xmax>
			<ymax>375</ymax>
		</box>
	</object>
	<object>
		<name>PIG</name>
		<box>
			<xmin>643</xmin>
			<ymin>254</ymin>
			<xmax>655</xmax>
			<ymax>265</ymax>
		</box>
	</object>
	<object>
		<name>PIG</name>
		<box>
			<xmin>343</xmin>
			<ymin>274</ymin>
			<xmax>356</xmax>
			<ymax>284</ymax>
		</box>
	</object>
	<object>
		<name>PIG</name>
		<box>
			<xmin>562</xmin>
			<ymin>254</ymin>
			<xmax>575</xmax>
			<ymax>265</ymax>
		</box>
	</object>
	<object>
		<name>PIG</name>
		<box>
			<xmin>399</xmin>
			<ymin>273</ymin>
			<xmax>412</xmax>
			<ymax>283</ymax>
		</box>
	</object>
	<object>
		<name>PIG</name>
		<box>
			<xmin>610</xmin>
			<ymin>254</ymin>
			<xmax>623</xmax>
			<ymax>265</ymax>
		</box>
	</object>
	<object>
		<name>PIG</name>
		<box>
			<xmin>469</xmin>
			<ymin>310</ymin>
			<xmax>482</xmax>
			<ymax>320</ymax>
		</box>
	</object>
</annotation>
